[
	{
		"email": "matias.rosenstein00@gmail.com",
		"nombre": "Matias",
		"contrase単a": "test",
		"tipo": "Inversor",
		"dinero": 6500
	},
	{
		"email": "test@test",
		"nombre": "Tester",
		"contrase単a": "test",
		"tipo": "Creador"
	},
	{
		"nombre": "Matias",
		"apellido": "Rosenstein",
		"email": "matias.rosen@cliente.com",
		"dni": 12345678,
		"nacimiento": "2023-05-05",
		"genero": "hombre",
		"telefono": 12345678,
		"direccion": "Hola 123",
		"contrase単a": "test123",
		"tipo": "Creador"
	},
	{
		"nombre": "Fran",
		"apellido": "Lagares",
		"email": "fran@lagares",
		"dni": 12345678,
		"nacimiento": "2023-06-01",
		"genero": "hombre",
		"telefono": 1234567890,
		"direccion": "123123",
		"contrase単a": "Fran",
		"tipo": "Inversor",
		"dinero": 99999999
	}
]